Compiled from "Exercise37_BytecodeInspection.java"
public class Exercise37_BytecodeInspection {
  public Exercise37_BytecodeInspection();
    Code:
       0: aload_0
       1: invokespecial #1                  // Method java/lang/Object."<init>":()V
       4: return

  public int calculateSum(int, int);
    Code:
       0: iload_1
       1: iload_2
       2: iadd
       3: istore_3
       4: iload_3
       5: ireturn

  public static void main(java.lang.String[]);
    Code:
       0: new           #7                  // class Exercise37_BytecodeInspection
       3: dup
       4: invokespecial #9                  // Method "<init>":()V
       7: astore_1
       8: aload_1
       9: bipush        15
      11: bipush        25
      13: invokevirtual #10                 // Method calculateSum:(II)I
      16: istore_2
      17: getstatic     #14                 // Field java/lang/System.out:Ljava/io/PrintStream;
      20: iload_2
      21: invokedynamic #20,  0             // InvokeDynamic #0:makeConcatWithConstants:(I)Ljava/lang/String;
      26: invokevirtual #24                 // Method java/io/PrintStream.println:(Ljava/lang/String;)V
      29: getstatic     #14                 // Field java/lang/System.out:Ljava/io/PrintStream;
      32: ldc           #30                 // String \nInstructions to inspect bytecode:\n1. Open a terminal in this directory.\n2. Run: javac Exercise37_BytecodeInspection.java\n3. Run: javap -c Exercise37_BytecodeInspection\n4. Observe the JVM instructions (iload, iadd, ireturn, etc.) in the output.
      34: invokevirtual #24                 // Method java/io/PrintStream.println:(Ljava/lang/String;)V
      37: return
}
